pac_bayes_toolbox/.DS_Store
pac_bayes_toolbox/__init__.py
pac_bayes_toolbox/kernel.py
pac_bayes_toolbox/pac_bayes_toolbox.py
pac_bayes_toolbox-0.1.0.dist-info/LICENSE
pac_bayes_toolbox-0.1.0.dist-info/METADATA
pac_bayes_toolbox-0.1.0.dist-info/WHEEL
pac_bayes_toolbox-0.1.0.dist-info/RECORD
